openbb_bls/__init__.py
openbb_bls/assets/__init__.py
openbb_bls/assets/bed_codes.json
openbb_bls/assets/bed_series.xz
openbb_bls/assets/bls_assets.json
openbb_bls/assets/cpi_codes.json
openbb_bls/assets/cpi_series.xz
openbb_bls/assets/cps_codes.json
openbb_bls/assets/cps_series.xz
openbb_bls/assets/ec_codes.json
openbb_bls/assets/ec_series.xz
openbb_bls/assets/ip_codes.json
openbb_bls/assets/ip_series.xz
openbb_bls/assets/jolts_codes.json
openbb_bls/assets/jolts_series.xz
openbb_bls/assets/lfs_codes.json
openbb_bls/assets/lfs_series.xz
openbb_bls/assets/nfp_codes.json
openbb_bls/assets/nfp_series.xz
openbb_bls/assets/pce_codes.json
openbb_bls/assets/pce_series.xz
openbb_bls/assets/ppi_codes.json
openbb_bls/assets/ppi_series.xz
openbb_bls/assets/sla_codes.json
openbb_bls/assets/sla_series.xz
openbb_bls/assets/tu_codes.json
openbb_bls/assets/tu_series.xz
openbb_bls/assets/wages_codes.json
openbb_bls/assets/wages_series.xz
openbb_bls/models/__init__.py
openbb_bls/models/search.py
openbb_bls/models/series.py
openbb_bls/utils/__init__.py
openbb_bls/utils/constants.py
openbb_bls/utils/helpers.py
openbb_bls-1.1.2.dist-info/METADATA
openbb_bls-1.1.2.dist-info/WHEEL
openbb_bls-1.1.2.dist-info/entry_points.txt
openbb_bls-1.1.2.dist-info/RECORD
